{"nrows": 177305, "colunas": ["ano", "zona", "faixa", "relacao", "grupo", "natureza", "fatal", "orientacao", "periodo", "hora", "local"], "rotulos": {"ano": ["2024", "2025", "2026"], "zona": ["Centro", "Norte", "Sul", "Leste", "Oeste", "n/i"], "faixa": ["0-11", "12-17", "18-24", "25-29", "30-39", "40-49", "50-59", "60+", "n/i"], "relacao": ["União estável", "Casamento", "Envolvimento amoroso", "Parentesco", "Convivência (amigo/vizinho/trabalho)", "Sem relação/outros", "Não informado"], "grupo": ["Física", "Psicológica", "Moral", "Sexual", "Patrimonial", "Medida protetiva"], "natureza": ["Ameaça", "Calúnia - Difamação - Injúria", "Lesão Corporal Dolosa", "Dano", "Perseguir", "Descumprimento De Medida Protetiva De Urgência", "Maus Tratos", "Outros C/C/ Dignidade Sexual", "Violência Psicológica Contra A Mulher", "Divulgação De Fotos/Videos Íntimos", "Invasão De Domicílio", "Constrangimento Ilegal"], "fatal": ["Não fatal", "Fatal"], "orientacao": ["Heterossexual", "Homossexual", "Bissexual", "Outras", "Não informado"], "periodo": ["madrugada", "manhã", "tarde", "noite", "n/i"], "local": ["Residência", "Via pública", "Condomínio", "Internet", "Comércio/serviços", "Transporte/terminal", "Outros", "n/i"]}, "cobertura_coord": 0.324, "pop_zonas": {"0": 423536, "1": 2208963, "2": 3735554, "3": 3991262, "4": 1092684}}